odoo9_addon_website_blog_excerpt_img-9.0.1.0.0-py2.7-nspkg.pth
odoo9_addon_website_blog_excerpt_img-9.0.1.0.0.dist-info/DESCRIPTION.rst
odoo9_addon_website_blog_excerpt_img-9.0.1.0.0.dist-info/METADATA
odoo9_addon_website_blog_excerpt_img-9.0.1.0.0.dist-info/RECORD
odoo9_addon_website_blog_excerpt_img-9.0.1.0.0.dist-info/WHEEL
odoo9_addon_website_blog_excerpt_img-9.0.1.0.0.dist-info/metadata.json
odoo9_addon_website_blog_excerpt_img-9.0.1.0.0.dist-info/namespace_packages.txt
odoo9_addon_website_blog_excerpt_img-9.0.1.0.0.dist-info/top_level.txt
odoo_addons/website_blog_excerpt_img/README.rst
odoo_addons/website_blog_excerpt_img/__init__.py
odoo_addons/website_blog_excerpt_img/__openerp__.py
odoo_addons/website_blog_excerpt_img/i18n/es.po
odoo_addons/website_blog_excerpt_img/i18n/fr.po
odoo_addons/website_blog_excerpt_img/i18n/sl.po
odoo_addons/website_blog_excerpt_img/images/style-default.png
odoo_addons/website_blog_excerpt_img/models/__init__.py
odoo_addons/website_blog_excerpt_img/models/blog_post.py
odoo_addons/website_blog_excerpt_img/static/description/icon.png
odoo_addons/website_blog_excerpt_img/static/src/css/website_blog_excerpt_img.sass
odoo_addons/website_blog_excerpt_img/templates/assets.xml
odoo_addons/website_blog_excerpt_img/templates/blog.xml
odoo_addons/website_blog_excerpt_img/tests/__init__.py
odoo_addons/website_blog_excerpt_img/tests/test_html.py
