Metadata-Version: 2.0
Name: odoo9-addon-website-blog-excerpt-img
Version: 9.0.1.0.0
Summary: New layout for blog summary, including an excerpt and image
Home-page: https://grupoesoc.es
Author: Grupo ESOC Ingeniería de Servicios, Odoo Community Association (OCA)
Author-email: support@odoo-community.org
License: LGPL-3
Platform: UNKNOWN
Classifier: Programming Language :: Python
Classifier: Framework :: Odoo
Classifier: License :: OSI Approved :: GNU Lesser General Public License v3 (LGPLv3)
Requires-Python: ~=2.7
Requires-Dist: odoo (<9.1a,>=9.0a)
Requires-Dist: odoo9-addon-html-image-url-extractor
Requires-Dist: odoo9-addon-html-text
